<?xml version="1.0" encoding="UTF-8"?>
<Caracteristica>
  <caracteristica>
    <NOMECARACTERISTICA>Angulo Lordose Lombar</NOMECARACTERISTICA>
  </caracteristica>
  <caracteristica>
    <NOMECARACTERISTICA>Grau de Espondilolistese</NOMECARACTERISTICA>
  </caracteristica>
  <caracteristica>
    <NOMECARACTERISTICA>Incidencia Pelvica</NOMECARACTERISTICA>
  </caracteristica>
  <caracteristica>
    <NOMECARACTERISTICA>Inclinacao Sacral</NOMECARACTERISTICA>
  </caracteristica>
  <caracteristica>
    <NOMECARACTERISTICA>Raio Pelvico</NOMECARACTERISTICA>
  </caracteristica>
  <caracteristica>
    <NOMECARACTERISTICA>Versao Pelvica</NOMECARACTERISTICA>
  </caracteristica>
</Caracteristica>